{
    "vue template init": {
        "prefix": "vue-template",
        "body": [
            "<template>",
            "\t$0",
            "</template>",
            "<script>",
            "\texport default {",
            "\t\tname:'$0',",
            "\t\tdata() {",
            "\t\t\treturn {",
            "\t\t\t\t$0",
            "\t\t\t}",
            "\t\t}",
            "\t}",
            "</script>",
            "<style lang=\"$1\" scoped>",
            "\t$0",
            "</style>"
        ],
        "description": "vue component templates"
    },
    "iview template init": {
        "prefix": "iview-template",
        "body": [
            "<style scoped>",

            ".layout{",
                "\tborder: 1px solid #d7dde4;",
                "\tbackground: #f5f7f9;",
            "}",
            ".layout-logo{",
                "\twidth: 100px;",
                "\theight: 30px;",
                "\tbackground: #5b6270;",
                "\tborder-radius: 3px;",
                "\tfloat: left;",
                "\tposition: relative;",
                "\ttop: 15px;",
                "\tleft: 20px;",
            "}",
            ".layout-nav{",
                "\twidth: 420px;",
                "\tmargin: 0 auto;",
            "}",
            ".layout-assistant{",
                "\twidth: 300px;",
                "\tmargin: 0 auto;",
                "\theight: inherit;",
            "}",
            ".layout-breadcrumb{",
                "\tpadding: 10px 15px 0;",
            "}",
            ".layout-content{",
                "\tmin-height: 200px;",
                "\tmargin: 15px;",
                "\toverflow: hidden;",
                "\tbackground: #fff;",
                "\tborder-radius: 4px;",
            "}",
            ".layout-content-main{",
                "\tpadding: 10px;",
            "}",
            ".layout-copy{",
                "\ttext-align: center;",
                "\tpadding: 10px 0 20px;",
                "\tcolor: #9ea7b4;",
            "}",
        "</style>",
        "<template>",
            "\t<div class=\"layout\">",
                "\t\t<Menu mode=\"horizontal\" theme=\"dark\" active-name=\"1\">",
                    "\t\t\t<div class=\"layout-logo\"></div>",
                    "\t\t\t<div class=\"layout-nav\">",
                        "\t\t\t\t<MenuItem name=\"1\">",
                            "\t\t\t\t\t<Icon type=\"ios-navigate\"></Icon>",
                            "\t\t\t\t\tItem 1",
                        "\t\t\t\t</MenuItem>",
                        "\t\t\t\t<MenuItem name=\"2\">",
                            "\t\t\t\t\t<Icon type=\"ios-keypad\"></Icon>",
                            "\t\t\t\t\tItem 2",
                        "\t\t\t\t</MenuItem>",
                        "\t\t\t\t<MenuItem name=\"3\">",
                            "\t\t\t\t\t<Icon type=\"ios-analytics\"></Icon>",
                            "\t\t\t\t\tItem 3",
                        "\t\t\t\t</MenuItem>",
                        "\t\t\t\t<MenuItem name=\"4\">",
                            "\t\t\t\t\t<Icon type=\"ios-paper\"></Icon>",
                            "\t\t\t\t\tItem 4",
                        "\t\t\t\t</MenuItem>",
                    "\t\t\t</div>",
                "\t\t</Menu>",
                "\t\t<Menu mode=\"horizontal\" active-name=\"1\">",
                    "\t\t\t<div class=\"layout-assistant\">",
                        "\t\t\t\t<MenuItem name=\"1\">Option 1</MenuItem>",
                        "\t\t\t\t<MenuItem name=\"2\">Option 2</MenuItem>",
                        "\t\t\t\t<MenuItem name=\"3\">Option 3</MenuItem>",
                    "\t\t\t</div>",
                "\t\t</Menu>",
                "\t\t<div class=\"layout-breadcrumb\">",
                    "\t\t\t<Breadcrumb>",
                        "\t\t\t\t<BreadcrumbItem href=\"#\">Home</BreadcrumbItem>",
                        "\t\t\t\t<BreadcrumbItem href=\"#\">Projects</BreadcrumbItem>",
                        "\t\t\t\t<BreadcrumbItem>iView</BreadcrumbItem>",
                    "\t\t\t</Breadcrumb>",
                "\t\t</div>",
                "\t\t<div class=\"layout-content\">",
                    "\t\t\t<div class=\"layout-content-main\">Content</div>",
                "\t\t</div>",
                "\t\t<div class=\"layout-copy\">",
                    "\t\t\t2011-2016 &copy; TalkingData",
                "\t\t</div>",
            "\t</div>",
        "</template>",
        "<script>",
            "\texport default {",
                "\t\t",
            "\t}",
        "</script>"
        ]
    }
}
